<?xml version="1.0" encoding="UTF-8" standalone="no"?>
<!--
+~~~~~~~~~~~~~~~~~~~~~~~~~~~~~~~~~~~~~~~~~~~~~~~~~~~~~~~~~~~~~~~~~~~~~~~~~~~~+
| This file is part of the Agavi package.                                    |
| Copyright (c) 2006 the Agavi Project.                                      |
+~~~~~~~~~~~~~~~~~~~~~~~~~~~~~~~~~~~~~~~~~~~~~~~~~~~~~~~~~~~~~~~~~~~~~~~~~~~~+
-->
<configurations>
	<configuration>
		<cachings>
			<caching name="categories.Browse" enabled="true">
				<action></action>
				<groups>
					<group name="categories" />
					<group name="id" source="request.parameter" />
					<group name="LANG" source="constant" />
					<group name="admin" source="user.credential" />
				</groups>
				<decorator include="false">
					<slots>
						<slot>breadcrumb</slot>
					</slots>
					<variables>
						<variable>_title</variable>
						<variable>_section</variable>
					</variables>
				</decorator>
				<views>
					<whitelists>
						<whitelist>Success</whitelist>
					</whitelists>
				</views>

				<variables>
					<variable name="categoryId" source="request.attribute" />
					<variable name="isRootCat" source="request.attribute" />
				</variables>
			</caching>
		</cachings>
	</configuration>
</configurations>

