<?xml version="1.0" encoding="UTF-8" standalone="no"?>
<configurations xmlns="http://agavi.org/agavi/1.0/config">

	<configuration>

		<loggers default="any">

			<!-- logs only DEBUG messages -->
			<logger name="any" class="AgaviLogger" level="AgaviLogger::ALL">
				<appenders>
					<appender>DebugLogAppender</appender>
				</appenders>
			</logger>

		</loggers>
		<appenders>

			<!--
				Debug logs are rotated in a 7 day (AgaviRotatingFileLoggerAppender default) cycle
				Use 'cycle' parameter to alter the cycle.
			-->
			<appender name="DebugLogAppender" class="AgaviRotatingFileLoggerAppender" layout="PassthruLayout">
				<parameters>
					<parameter name="dir">%core.app_dir%/log/</parameter>
					<parameter name="prefix">debug-</parameter>
				</parameters>
			</appender>
		</appenders>

		<layouts>
			<layout name="PassthruLayout" class="AgaviTimestampLoggerLayout" />
		</layouts>

	</configuration>

</configurations>